agentsface/__init__.py
agentsface-0.2.0.dist-info/METADATA
agentsface-0.2.0.dist-info/WHEEL
agentsface-0.2.0.dist-info/RECORD
