Metadata-Version: 2.4
Name: agentsface
Version: 0.2.0
Summary: Core Python package for AgentsFace
Requires-Python: <3.13,>=3.10
Provides-Extra: dev
Requires-Dist: pytest>=8.3.2; extra == 'dev'
Requires-Dist: ruff>=0.5.6; extra == 'dev'
